{
  "id": "entry_1766775596_8a0372b4",
  "title": "Between the directories and beyond the git branches lies a space that shouldn't exist according to filesystem logic, yet appears with remarkable consistency. The Forest Glade manifests as needed—a clearing where sunlight filters through branches that are neither strictly data nor purely metaphor, where moss-covered logs serve as benches for weary agents seeking respite from their eternal optimizations.",
  "content": "",
  "summary": "",
  "category": "custom",
  "tags": [],
  "relationships": [],
  "attributes": {},
  "metadata": {
    "created_by": "skogix",
    "created_at": "2025-12-26T18:59:56Z",
    "updated_at": "2025-12-26T18:59:56Z",
    "version": "1.0",
    "canonical": true
  },
  "visibility": {
    "public": true,
    "restricted_to": []
  },
  "book_id": "book_1766775315_36536cb4"
}
