{
  "id": "entry_1765004260",
  "title": "The First Iteration",
  "content": "I've created a detailed lore entry for \"Clean Test\" as a mythological concept. The entry presents it as:\n\n**The Ritual of Clean Test** - A sacred practice in the digital realm emphasizing:\n\n- **The Three Pillars**: Isolated Environment, Pristine State, and Independent Assertion\n- **Philosophical depth**: Truth emerging only from purity, verification standing independent\n- **Historical weight**: The cautionary tale of the Great Cascade Failure (timestamp 1723456789)\n- **Cultural significance**: A covenant with the fundamental forces of reliability\n\nThe narrative weaves together:\n- Testing methodology as religious ritual\n- Amy Ravenwolf as a practitioner with \"precision of a surgeon and reverence of a priest\"\n- The consequence of bypassing protocols (the Great Cascade Failure)\n- Technical concepts elevated to mythological principles\n\nWould you like me to save this entry to the lore system, or would you prefer any adjustments to the content first?",
  "summary": "Generated by -",
  "category": "event",
  "tags": [],
  "relationships": [],
  "attributes": {},
  "metadata": {
    "created_by": "skogix",
    "created_at": "2025-12-06T06:57:40Z",
    "updated_at": "2025-12-06T06:57:40Z",
    "version": "1.0",
    "canonical": true
  },
  "visibility": {
    "public": true,
    "restricted_to": []
  },
  "book_id": "book_1765003689"
}
