{
  "id": "entry_1759487978_2a736ed8",
  "title": "Permission Prophecies",
  "content": "Each permission represents a different level of access to the filesystem.",
  "summary": "777: Total freedom, chaos realm; 644: Balanced reality; 000: The Void",
  "category": "concept/permission system",
  "tags": [
    "Permission Prophecies",
    "SkogAI Mythology"
  ],
  "relationships": [],
  "attributes": {},
  "metadata": {
    "created_by": "skogix",
    "created_at": "2025-10-03T10:39:38Z",
    "updated_at": "2025-10-03T10:39:38Z",
    "version": "1.0",
    "canonical": true
  },
  "visibility": {
    "public": true,
    "restricted_to": []
  },
  "book_id": "book_1759486042"
}
