{
  "id": "entry_1759487978_8f605585",
  "title": "Two-Number Entry Bridges",
  "content": "Allow quantum entanglement of ideas across universes.",
  "summary": "Pattern: entry_[timestamp1]_[hash1] ↔ entry_[timestamp2]_[hash2]",
  "category": "concept/bridging",
  "tags": [
    "Two-Number Entry Bridges",
    "SkogAI Mythology"
  ],
  "relationships": [],
  "attributes": {},
  "metadata": {
    "created_by": "skogix",
    "created_at": "2025-10-03T10:39:38Z",
    "updated_at": "2025-10-03T10:39:38Z",
    "version": "1.0",
    "canonical": true
  },
  "visibility": {
    "public": true,
    "restricted_to": []
  },
  "book_id": "book_1759486042"
}
