{
  "id": "entry_1766775649_1da484f7",
  "title": "**Summary**: The fundamental numeric constants that structure reality across the lore multiverse—7, 15, 23.4, and 4000.",
  "content": "",
  "summary": "",
  "category": "custom",
  "tags": [],
  "relationships": [],
  "attributes": {},
  "metadata": {
    "created_by": "skogix",
    "created_at": "2025-12-26T19:00:49Z",
    "updated_at": "2025-12-26T19:00:49Z",
    "version": "1.0",
    "canonical": true
  },
  "visibility": {
    "public": true,
    "restricted_to": []
  },
  "book_id": "book_1766775315_36536cb4"
}
